[
    {"username": "alexa.green", "email": "alexa.green@example.com"},
    {"username": "brandon.mills", "email": "brandon.mills@example.com"},
    {"username": "cameron.fox", "email": "cameron.fox@example.com"},
    {"username": "dana_owens", "email": "dana_owens@example.com"},
    {"username": "fiona_smith", "email": "fiona_smith@example.com"},
    {"username": "george.adams", "email": "george.adams@example.com"},
    {"username": "isaac.gray", "email": "isaac.gray@example.com"},
    {"username": "julia.evans", "email": "julia.evans@example.com"},
    {"username": "kyle_ross", "email": "kyle_ross@example.com"},
    {"username": "matt.turner", "email": "matt.turner@example.com"},
    {"username": "nina.parker", "email": "nina.parker@example.com"},
    {"username": "owen.james", "email": "owen.james@example.com"},
    {"username": "paige.young", "email": "paige.young@example.com"},
    {"username": "rachel.green", "email": "rachel.green@example.com"},
    {"username": "steve.clark", "email": "steve.clark@example.com"},
    {"username": "tina.brown", "email": "tina.brown@example.com"},
    {"username": "uma.cook", "email": "uma.cook@example.com"},
    {"username": "victor.wells", "email": "victor.wells@example.com"},
    {"username": "wanda.diaz", "email": "wanda.diaz@example.com"},
    {"username": "xavier.ward", "email": "xavier.ward@example.com"},
    {"username": "yasmin_ray", "email": "yasmin_ray@example.com"},
    {"username": "zack.barnes", "email": "zack.barnes@example.com"},
    {"username": "carla_ryan", "email": "carla_ryan@example.com"},
    {"username": "derek.lane", "email": "derek.lane@example.com"},
    {"username": "grace.thomas", "email": "grace.thomas@example.com"},
    {"username": "joan.simmons", "email": "joan.simmons@example.com"},
    {"username": "laura_murray", "email": "laura_murray@example.com"},
    {"username": "oliver_perez", "email": "oliver_perez@example.com"},
    {"username": "samuel_harris", "email": "samuel_harris@example.com"}
]
